MANIFEST.in
README.md
README.txt
requirements.txt
setup.py
aws_es_auth_proxy/__init__.py
aws_es_auth_proxy/config.py
aws_es_auth_proxy.egg-info/PKG-INFO
aws_es_auth_proxy.egg-info/SOURCES.txt
aws_es_auth_proxy.egg-info/dependency_links.txt
aws_es_auth_proxy.egg-info/requires.txt
aws_es_auth_proxy.egg-info/top_level.txt
bin/aws-es-auth-proxy