Metadata-Version: 1.1
Name: aws-es-auth-proxy
Version: 0.1.5
Summary: A simple HTTP proxy to authenticato to AWS Elasticsearch cluster.
Home-page: http://packages.python.org/an_example_pypi_project
Author: Luca Agostini
Author-email: agostini.luca@gmail.com
License: GPL
Keywords: aws elasticsearch auth proxy
Platform: UNKNOWN
Classifier: Development Status :: 3 - Alpha
Classifier: Topic :: Internet :: Proxy Servers
Classifier: License :: OSI Approved :: GNU Lesser General Public License v3 (LGPLv3)
